.testr.conf
AUTHORS
ChangeLog
LICENSE
README.rst
requirements.txt
setup.cfg
setup.py
test-requirements.txt
tox.ini
doc/source/conf.py
doc/source/index.rst
ospurge/__init__.py
ospurge/exceptions.py
ospurge/main.py
ospurge/utils.py
ospurge.egg-info/PKG-INFO
ospurge.egg-info/SOURCES.txt
ospurge.egg-info/dependency_links.txt
ospurge.egg-info/entry_points.txt
ospurge.egg-info/not-zip-safe
ospurge.egg-info/pbr.json
ospurge.egg-info/requires.txt
ospurge.egg-info/top_level.txt
ospurge/resources/__init__.py
ospurge/resources/base.py
ospurge/resources/cinder.py
ospurge/resources/glance.py
ospurge/resources/neutron.py
ospurge/resources/nova.py
ospurge/resources/swift.py
ospurge/tests/__init__.py
ospurge/tests/test_main.py
ospurge/tests/test_utils.py
ospurge/tests/resources/__init__.py
ospurge/tests/resources/test_base.py
ospurge/tests/resources/test_cinder.py
ospurge/tests/resources/test_glance.py
ospurge/tests/resources/test_neutron.py
ospurge/tests/resources/test_nova.py
ospurge/tests/resources/test_swift.py
tools/func-tests.sh
tools/populate.sh
tools/print_order.py
tools/stress.sh