Metadata-Version: 1.1
Name: ospurge
Version: 2.0.0
Summary: OpenStack resources cleanup script
Home-page: https://github.com/openstack/ospurge
Author: The OSPurge contributors
Author-email: UNKNOWN
License: Apache-2
Keywords: openstack
Platform: UNKNOWN
Classifier: Development Status :: 5 - Production/Stable
Classifier: Environment :: Console
Classifier: Environment :: OpenStack
Classifier: Intended Audience :: Developers
Classifier: Intended Audience :: Information Technology
Classifier: Intended Audience :: System Administrators
Classifier: License :: OSI Approved :: Apache Software License
Classifier: Operating System :: POSIX :: Linux
Classifier: Programming Language :: Python :: 3
Classifier: Programming Language :: Python :: 3.5
